README.rst
setup.py
src/pyifttt/__init__.py
src/pyifttt/webhook.py
src/pyifttt.egg-info/PKG-INFO
src/pyifttt.egg-info/SOURCES.txt
src/pyifttt.egg-info/dependency_links.txt
src/pyifttt.egg-info/requires.txt
src/pyifttt.egg-info/top_level.txt