Metadata-Version: 1.1
Name: pyifttt
Version: 0.1.2
Summary: Python Wrapper for IFTTT Webhook interaction.
Home-page: https://github.com/RubenBranco/pyifttt
Author: Ruben Branco
Author-email: ruben.branco@outlook.pt
License: GPLv3
Keywords: ifttt,webhook
Platform: UNKNOWN
Classifier: Development Status :: 3 - Alpha
Classifier: License :: OSI Approved :: MIT License
Classifier: Programming Language :: Python :: 3
